pydictable/__init__.py
pydictable/core.py
pydictable/field.py
pydictable/generic.py
pydictable/json_schema.py
pydictable/test_core.py
pydictable/test_field.py
pydictable/test_generic.py
pydictable/test_json_schema.py
pydictable/type.py
pydictable-2.3.0.dist-info/licenses/LICENSE
pydictable-2.3.0.dist-info/METADATA
pydictable-2.3.0.dist-info/WHEEL
pydictable-2.3.0.dist-info/top_level.txt
pydictable-2.3.0.dist-info/RECORD
