Metadata-Version: 2.4
Name: pydictable
Version: 2.3.0
Summary: Make your classes from/to dict
Home-page: https://github.com/pskd73/pydictable.git
Author: Pramod Kumar
Author-email: pramodkumar.damam73@gmail.com
License-File: LICENSE
Dynamic: author
Dynamic: author-email
Dynamic: description
Dynamic: description-content-type
Dynamic: home-page
Dynamic: license-file
Dynamic: summary
